{
  "customers": [
    {
      "id": 1,
      "customerName": "Nguyễn Hữu Thức",
      "dayOfBirth": "05-01-1996",
      "idCard": "201757575",
      "customerPhone": "0936363636",
      "customerEmail": "thuc@gmail.com",
      "customerAddress": "149 Lê Đình Lý",
      "customerType": {
        "id": 1,
        "customerTypeName": "Platinum"
      }
    },
    {
      "customerName": "TuấnNC",
      "dayOfBirth": "1995-01-01",
      "idCard": "201656565",
      "customerPhone": "0343434343",
      "customerEmail": "tuannc@gmail.com",
      "customerAddress": "01 Ngô Thị Nhậm",
      "customerType": {
        "id": 2,
        "customerTypeName": "Gold"
      },
      "id": 3
    },
    {
      "customerName": "VinhVN",
      "dayOfBirth": "1998-01-01",
      "idCard": "202454545",
      "customerPhone": "0955686868",
      "customerEmail": "nhuvinh@gmail.com",
      "customerAddress": "143 Phạm Như Xương",
      "customerType": {
        "id": 1,
        "customerTypeName": "Platinum"
      },
      "id": 4
    }
  ],
  "customerTypes": [
    {
      "id": 1,
      "customerTypeName": "Platinum"
    },
    {
      "id": 2,
      "customerTypeName": "Gold"
    },
    {
      "id": 3,
      "customerTypeName": "Silver"
    },
    {
      "id": 4,
      "customerTypeName": "Member"
    }
  ],
  "facility": [
    {
      "id": 1,
      "name": "Villa Beach Front",
      "area": 25000,
      "cost": 10000000,
      "maxPeople": 10,
      "standardRoom": "Vip",
      "descriptionOtherConvenience": "Có hồ bơi",
      "poolArea": 500,
      "numberOfFloors": 4,
      "facilityFree": "Karaoke",
      "rentType": {
        "id": 1,
        "name": "Year"
      },
      "facilityType": {
        "id": 1,
        "name": "Villa"
      }
    },
    {
      "id": 2,
      "name": "House Princess 01",
      "area": 25000,
      "cost": 10000000,
      "maxPeople": 10,
      "standardRoom": "Vip",
      "descriptionOtherConvenience": "Có hồ bơi",
      "poolArea": 500,
      "numberOfFloors": 4,
      "facilityFree": "Massage",
      "rentType": {
        "id": 2,
        "name": "Month"
      },
      "facilityType": {
        "id": 2,
        "name": "House"
      }
    },
    {
      "id": 3,
      "name": "Room Twin 01",
      "area": 5000,
      "cost": 1000000,
      "maxPeople": 3,
      "standardRoom": "Classic",
      "descriptionOtherConvenience": "Có Wifi, nước nóng",
      "poolArea": 0,
      "numberOfFloors": 4,
      "facilityFree": null,
      "rentType": {
        "id": 3,
        "name": "Day"
      },
      "facilityType": {
        "id": 2,
        "name": "House"
      }
    }
  ],
  "cars": [
    {
      "id": 1,
      "garageName": "Mai Linh",
      "garagePhone": "0936363637",
      "garageEmail": "mailinh@gmail.com",
      "carCompany": {
        "id": 1,
        "licensePlates": "1231",
        "carType": "Giường nằm 34 chỗ",
        "departurePoint": "Đà Nẵng",
        "destination": "Hà Nội",
        "startTime": "07:00",
        "hourEnds": "16:00"
      }
    },
    {
      "id": 2,
      "garageName": "Hoàng Long",
      "garagePhone": "0925252525",
      "garageEmail": "hoanglong@gmail.com",
      "carCompany": {
        "id": 2,
        "licensePlates": "5678",
        "carType": "Giường nằm 20 chỗ",
        "departurePoint": "Đà Nẵng",
        "destination": "Quảng Bình",
        "startTime": "08:00",
        "hourEnds": "18:00"
      }
    },
    {
      "id": 3,
      "garageName": "Mai Linh",
      "garagePhone": "0936363637",
      "garageEmail": "mailinh@gmail.com",
      "carCompany": {
        "id": 3,
        "licensePlates": "1231",
        "carType": "Giường nằm 34 chỗ",
        "departurePoint": "Nha Trang",
        "destination": "Thanh Hoá",
        "startTime": "09:00",
        "hourEnds": "15:00"
      }
    },
    {
      "id": 4,
      "garageName": "Hoàng Long",
      "garagePhone": "0925252525",
      "garageEmail": "hoanglong@gmail.com",
      "carCompany": {
        "id": 4,
        "licensePlates": "5678",
        "carType": "Giường nằm 20 chỗ",
        "departurePoint": "Quảng Bình",
        "destination": "Đà Lạt",
        "startTime": "07:00",
        "hourEnds": "16:00"
      }
    }
  ],
  "carCompanys": [
    {
      "id": 1,
      "licensePlates": "1234",
      "carType": "Giường nằm 20 chỗ",
      "departurePoint": "Đà Nẵng",
      "destination": "Hà Nội",
      "startTime": "07:00",
      "hourEnds": "15:00"
    },
    {
      "id": 2,
      "licensePlates": "5678",
      "carType": "Ghế ngồi 30 chỗ",
      "departurePoint": "Hà Nội",
      "destination": "Đà Nẵng",
      "startTime": "08:00",
      "hourEnds": "16:00"
    },
    {
      "id": 3,
      "licensePlates": "6789",
      "carType": "Giường nằm 34 chỗ",
      "departurePoint": "Nha Trang",
      "destination": "Thanh Hoá",
      "startTime": "09:00",
      "hourEnds": "17:00"
    },
    {
      "id": 4,
      "licensePlates": "2345",
      "carType": "Ghế ngồi 45 chỗ",
      "departurePoint": "Quảng Bình",
      "destination": "Đà Lạt",
      "startTime": "10:00",
      "hourEnds": "18:00"
    }
  ]
}
